nperf/__init__.py
nperf/__main__.py
nperf/shell.py
nperf/web.py
nperf-1.0.0.dist-info/DESCRIPTION.rst
nperf-1.0.0.dist-info/METADATA
nperf-1.0.0.dist-info/RECORD
nperf-1.0.0.dist-info/WHEEL
nperf-1.0.0.dist-info/entry_points.txt
nperf-1.0.0.dist-info/metadata.json
nperf-1.0.0.dist-info/top_level.txt
